unvibe/.DS_Store
unvibe/__init__.py
unvibe/__main__.py
unvibe/config.py
unvibe/core.py
unvibe/disk_cache.py
unvibe/llm.py
unvibe/log.py
unvibe/magic.py
unvibe/rand.py
unvibe/server.py
unvibe/state.py
unvibe/suite.py
unvibe/tests_container.py
unvibe/ui.html
unvibe/ui.py
unvibe-0.1.5.dist-info/LICENSE
unvibe-0.1.5.dist-info/METADATA
unvibe-0.1.5.dist-info/WHEEL
unvibe-0.1.5.dist-info/entry_points.txt
unvibe-0.1.5.dist-info/RECORD
