Metadata-Version: 2.3
Name: unvibe
Version: 0.1.5
Summary: Generate code from unit-tests
Author: Claudio Santini
Author-email: hireclaudio@gmail.com
Requires-Python: >=3.9,<4.0
Classifier: Programming Language :: Python :: 3
Classifier: Programming Language :: Python :: 3.9
Classifier: Programming Language :: Python :: 3.10
Classifier: Programming Language :: Python :: 3.11
Classifier: Programming Language :: Python :: 3.12
Classifier: Programming Language :: Python :: 3.13
Requires-Dist: anthropic (>=0.46.0,<0.47.0)
Requires-Dist: bigtree (>=0.25.1,<0.26.0)
Requires-Dist: google-genai (>=1.2.0,<2.0.0)
Requires-Dist: ollama (>=0.4.7,<0.5.0)
Requires-Dist: openai (>=1.64.0,<2.0.0)
Requires-Dist: pydot (>=3.0.4,<4.0.0)
Requires-Dist: rsa (==4.7)
Requires-Dist: yaspin (>=3.1.0,<4.0.0)
